swimlanefaker/__init__.py
swimlanefaker/base.py
swimlanefaker/datafaker.py
swimlanefaker/randomfaker.py
swimlanefaker/swimlanefaker.py
swimlanefaker/timefaker.py
swimlane_faker-0.2.0.dist-info/LICENSE
swimlane_faker-0.2.0.dist-info/METADATA
swimlane_faker-0.2.0.dist-info/WHEEL
swimlane_faker-0.2.0.dist-info/top_level.txt
swimlane_faker-0.2.0.dist-info/RECORD
