Metadata-Version: 2.1
Name: swimlane-faker
Version: 0.2.0
Summary: A Python package to generate fake data from provided input strings for use with Swimlane
Home-page: https://github.com/swimlane/swimlane-faker
Author: Swimlane
Author-email: info@swimlane.com
License: MIT
Keywords: swimlane
Platform: UNKNOWN
Requires-Python: >=2.6, !=3.0.*, !=3.1.*, !=3.2.*, <4
